velosaurus_sum/__init__.py
velosaurus_sum/calculator.py
velosaurus_sum-1.0.6.dist-info/METADATA
velosaurus_sum-1.0.6.dist-info/WHEEL
velosaurus_sum-1.0.6.dist-info/top_level.txt
velosaurus_sum-1.0.6.dist-info/RECORD
